payroll_1c.py
payroll_1c-0.3.2.dist-info/LICENSE
payroll_1c-0.3.2.dist-info/WHEEL
payroll_1c-0.3.2.dist-info/METADATA
payroll_1c-0.3.2.dist-info/RECORD
